{
  "Size": [
    3,
    4
  ],
  "Cells": [
    {
      "color": "B",
      "north": "B",
      "south": "D",
      "east": "N",
      "west": "B",
      "isSpawn": false
    },
    {
      "color": "B",
      "north": "B",
      "south": "W",
      "east": "N",
      "west": "N",
      "isSpawn": false
    },
    {
      "color": "B",
      "north": "B",
      "south": "D",
      "east": "D",
      "west": "N",
      "isSpawn": true
    },
    {
      "color": "G",
      "north": "B",
      "south": "D",
      "east": "B",
      "west": "D",
      "isSpawn": false
    },
    {
      "color": "R",
      "north": "D",
      "south": "B",
      "east": "N",
      "west": "B",
      "isSpawn": true
    },
    {
      "color": "R",
      "north": "W",
      "south": "D",
      "east": "W",
      "west": "N",
      "isSpawn": false
    },
    {
      "color": "Y",
      "north": "D",
      "south": "N",
      "east": "N",
      "west": "W",
      "isSpawn": false
    },
    {
      "color": "Y",
      "north": "D",
      "south": "N",
      "east": "B",
      "west": "N",
      "isSpawn": false
    },
    {
      "color": "X"
    },
    {
      "color": "W",
      "north": "D",
      "south": "B",
      "east": "D",
      "west": "B",
      "isSpawn": false
    },
    {
      "color": "Y",
      "north": "N",
      "south": "B",
      "east": "N",
      "west": "D",
      "isSpawn": false
    },
    {
      "color": "Y",
      "north": "N",
      "south": "B",
      "east": "B",
      "west": "N",
      "isSpawn": true
    }
  ]
}